pysheetsql/__init__.py
pysheetsql/manage_table.py
pysheetsql/start.py
pysheetsql/table.py
pysheetsql-0.1.dist-info/LICENSE
pysheetsql-0.1.dist-info/METADATA
pysheetsql-0.1.dist-info/WHEEL
pysheetsql-0.1.dist-info/top_level.txt
pysheetsql-0.1.dist-info/RECORD
