Metadata-Version: 2.1
Name: pysheetsql
Version: 0.1
Summary: A package for managing Google Sheets data with gspread
Author: Syed Abdullah Imam
Author-email: syedabdullahimam@example.com
Classifier: Programming Language :: Python :: 3
Classifier: License :: OSI Approved :: MIT License
Classifier: Operating System :: OS Independent
Requires-Python: >=3.6
License-File: LICENSE
Requires-Dist: gspread
Requires-Dist: google-auth
